{
	"info": {
		"_postman_id": "eaf27032-86c5-40a2-b886-046db3e8b254",
		"name": "Comments",
		"schema": "https://schema.getpostman.com/json/collection/v2.1.0/collection.json",
		"_exporter_id": "37356392",
		"_collection_link": "https://universal-star-958557.postman.co/workspace/DummyJSON_APITesting_Project~283bdf31-b0c5-4daf-820d-dca647687ef6/collection/46944925-eaf27032-86c5-40a2-b886-046db3e8b254?action=share&source=collection_link&creator=37356392"
	},
	"item": [
		{
			"name": "Get all comments",
			"event": [
				{
					"listen": "test",
					"script": {
						"exec": [
							"pm.test(\"check status code is 200\", function () {\r",
							"    pm.response.to.have.status(200);\r",
							"});\r",
							""
						],
						"type": "text/javascript",
						"packages": {}
					}
				}
			],
			"request": {
				"auth": {
					"type": "noauth"
				},
				"method": "GET",
				"header": [],
				"url": {
					"raw": "{{base_url}}/comments",
					"host": [
						"{{base_url}}"
					],
					"path": [
						"comments"
					]
				}
			},
			"response": []
		},
		{
			"name": "Gdet a comment ",
			"event": [
				{
					"listen": "test",
					"script": {
						"exec": [
							"pm.test(\"Status code is 200\", function () {\r",
							"    pm.response.to.have.status(200);\r",
							"});"
						],
						"type": "text/javascript",
						"packages": {}
					}
				}
			],
			"request": {
				"auth": {
					"type": "noauth"
				},
				"method": "GET",
				"header": [],
				"url": {
					"raw": "{{base_url}}/comments/1",
					"host": [
						"{{base_url}}"
					],
					"path": [
						"comments",
						"1"
					]
				}
			},
			"response": []
		},
		{
			"name": "Limit comments",
			"event": [
				{
					"listen": "test",
					"script": {
						"exec": [
							"pm.test(\"Status code is 200\", function () {\r",
							"    pm.response.to.have.status(200);\r",
							"});"
						],
						"type": "text/javascript",
						"packages": {}
					}
				}
			],
			"request": {
				"auth": {
					"type": "noauth"
				},
				"method": "GET",
				"header": [],
				"url": {
					"raw": "{{base_url}}/comments?limit=10&skip=10&select=body,postId",
					"host": [
						"{{base_url}}"
					],
					"path": [
						"comments"
					],
					"query": [
						{
							"key": "limit",
							"value": "10"
						},
						{
							"key": "skip",
							"value": "10"
						},
						{
							"key": "select",
							"value": "body,postId"
						}
					]
				}
			},
			"response": []
		},
		{
			"name": "comment by post ",
			"event": [
				{
					"listen": "test",
					"script": {
						"exec": [
							"pm.test(\"Status code is 200\", function () {\r",
							"    pm.response.to.have.status(200);\r",
							"});"
						],
						"type": "text/javascript",
						"packages": {}
					}
				}
			],
			"request": {
				"auth": {
					"type": "noauth"
				},
				"method": "GET",
				"header": [],
				"url": {
					"raw": "{{base_url}}/comments/post/6",
					"host": [
						"{{base_url}}"
					],
					"path": [
						"comments",
						"post",
						"6"
					]
				}
			},
			"response": []
		},
		{
			"name": "add a coment",
			"event": [
				{
					"listen": "test",
					"script": {
						"exec": [
							"pm.test(\"Status code is 200\", function () {\r",
							"    pm.response.to.have.status(200);\r",
							"});"
						],
						"type": "text/javascript",
						"packages": {}
					}
				}
			],
			"request": {
				"auth": {
					"type": "noauth"
				},
				"method": "POST",
				"header": [],
				"body": {
					"mode": "raw",
					"raw": "{\r\n    \"body\":\"This makes all sense to me!\",\r\n    \"postId\":3,\r\n    \"userId\":5\r\n}",
					"options": {
						"raw": {
							"language": "json"
						}
					}
				},
				"url": {
					"raw": "{{base_url}}/comments/add",
					"host": [
						"{{base_url}}"
					],
					"path": [
						"comments",
						"add"
					]
				}
			},
			"response": []
		},
		{
			"name": "update a comment ",
			"event": [
				{
					"listen": "test",
					"script": {
						"exec": [
							"pm.test(\"Status code is 200\", function () {\r",
							"    pm.response.to.have.status(200);\r",
							"});"
						],
						"type": "text/javascript",
						"packages": {}
					}
				}
			],
			"request": {
				"auth": {
					"type": "noauth"
				},
				"method": "PUT",
				"header": [],
				"body": {
					"mode": "raw",
					"raw": "{\r\n    \"body\":\"I think I should shift to the moon\"\r\n}",
					"options": {
						"raw": {
							"language": "json"
						}
					}
				},
				"url": {
					"raw": "{{base_url}}/comments/1",
					"host": [
						"{{base_url}}"
					],
					"path": [
						"comments",
						"1"
					]
				}
			},
			"response": []
		},
		{
			"name": "delete a comment ",
			"event": [
				{
					"listen": "test",
					"script": {
						"exec": [
							"pm.test(\"Status code is 200\", function () {\r",
							"    pm.response.to.have.status(200);\r",
							"});"
						],
						"type": "text/javascript",
						"packages": {}
					}
				}
			],
			"request": {
				"auth": {
					"type": "noauth"
				},
				"method": "DELETE",
				"header": [],
				"url": {
					"raw": "{{base_url}}/comments/1",
					"host": [
						"{{base_url}}"
					],
					"path": [
						"comments",
						"1"
					]
				}
			},
			"response": []
		}
	]
}